ecut/__init__.py
ecut/_queue.py
ecut/annealing.py
ecut/base_types.py
ecut/error_prune.py
ecut/graph_cut.py
ecut/graph_metrics.py
ecut/morphology.py
ecut/soma_detection.py
ecut/swc_handler.py
ecut/gcut_utils/LICENSE
ecut/gcut_utils/__init__.py
ecut/gcut_utils/distribution.py
ecut/gcut_utils/gof_distributions.json
ecut/gcut_utils/gof_mouse_distributions.json
E_Cut-0.2.0.dist-info/LICENSE
E_Cut-0.2.0.dist-info/METADATA
E_Cut-0.2.0.dist-info/NOTICE
E_Cut-0.2.0.dist-info/WHEEL
E_Cut-0.2.0.dist-info/top_level.txt
E_Cut-0.2.0.dist-info/RECORD
