Metadata-Version: 2.1
Name: E-Cut
Version: 0.2.0
Summary: Enhanced G-Cut algorithm on automated segmentation of interweaving neurons
Author-email: Zuohan Zhao <zzhmark@126.com>, Yufeng Liu <yufeng_liu@seu.edu.cn>
License: MIT License
Project-URL: GitHub Project, https://github.com/SEU-ALLEN-codebase/E-Cut
Project-URL: Documentation, https://SEU-ALLEN-codebase.github.io/E-Cut
Keywords: linear-programming,neuron-morphology,neuorn-tracing
Classifier: Programming Language :: Python :: 3
Classifier: License :: OSI Approved :: MIT License
Classifier: Operating System :: OS Independent
Requires-Python: >=3.10
License-File: LICENSE
License-File: NOTICE
Requires-Dist: numpy
Requires-Dist: scikit-learn
Requires-Dist: PuLP
Requires-Dist: scipy
Requires-Dist: scikit-image
Requires-Dist: tqdm
Requires-Dist: pandas
Provides-Extra: docs
Requires-Dist: pdoc ; extra == 'docs'
